ai3/__init__.py
ai3/models.py
ai3/utils/__init__.py
ai3/utils/load.py
ai3-0.0.0.dist-info/METADATA
ai3-0.0.0.dist-info/WHEEL
ai3-0.0.0.dist-info/top_level.txt
ai3-0.0.0.dist-info/RECORD
