Metadata-Version: 2.1
Name: ai3
Version: 0.0.0
Home-page: https://github.com/carlosarturoceron/ai3
Author: Carlos Linares
Author-email: oddskid@gmail.com
Requires-Python: >=3.8
Requires-Dist: requests
Requires-Dist: tensorflow
